financestuff/__init__.py
financestuff/return_calculator.py
financestuff-0.0.1.dist-info/METADATA
financestuff-0.0.1.dist-info/WHEEL
financestuff-0.0.1.dist-info/top_level.txt
financestuff-0.0.1.dist-info/RECORD
