Metadata-Version: 2.1
Name: financestuff
Version: 0.0.1
Summary: Finance Related
Home-page: UNKNOWN
Author: Sandip Sutariya
Author-email: UNKNOWN
License: UNKNOWN
Platform: UNKNOWN
Classifier: Programming Language :: Python :: 3
